{
  "1977_0": {
    "embedding_file": "embedding_1977_0.npy",
    "year": 1977,
    "topic": "general",
    "chunk_index": 0
  },
  "1978_0": {
    "embedding_file": "embedding_1978_0.npy",
    "year": 1978,
    "topic": "general",
    "chunk_index": 0
  },
  "1979_0": {
    "embedding_file": "embedding_1979_0.npy",
    "year": 1979,
    "topic": "general",
    "chunk_index": 0
  },
  "1980_0": {
    "embedding_file": "embedding_1980_0.npy",
    "year": 1980,
    "topic": "general",
    "chunk_index": 0
  },
  "1981_0": {
    "embedding_file": "embedding_1981_0.npy",
    "year": 1981,
    "topic": "general",
    "chunk_index": 0
  },
  "1982_0": {
    "embedding_file": "embedding_1982_0.npy",
    "year": 1982,
    "topic": "general",
    "chunk_index": 0
  },
  "1983_0": {
    "embedding_file": "embedding_1983_0.npy",
    "year": 1983,
    "topic": "general",
    "chunk_index": 0
  },
  "1984_0": {
    "embedding_file": "embedding_1984_0.npy",
    "year": 1984,
    "topic": "general",
    "chunk_index": 0
  },
  "1985_0": {
    "embedding_file": "embedding_1985_0.npy",
    "year": 1985,
    "topic": "general",
    "chunk_index": 0
  },
  "1986_0": {
    "embedding_file": "embedding_1986_0.npy",
    "year": 1986,
    "topic": "general",
    "chunk_index": 0
  },
  "1987_0": {
    "embedding_file": "embedding_1987_0.npy",
    "year": 1987,
    "topic": "general",
    "chunk_index": 0
  },
  "1988_0": {
    "embedding_file": "embedding_1988_0.npy",
    "year": 1988,
    "topic": "general",
    "chunk_index": 0
  },
  "1989_0": {
    "embedding_file": "embedding_1989_0.npy",
    "year": 1989,
    "topic": "general",
    "chunk_index": 0
  },
  "1990_0": {
    "embedding_file": "embedding_1990_0.npy",
    "year": 1990,
    "topic": "general",
    "chunk_index": 0
  },
  "1991_0": {
    "embedding_file": "embedding_1991_0.npy",
    "year": 1991,
    "topic": "general",
    "chunk_index": 0
  },
  "1992_0": {
    "embedding_file": "embedding_1992_0.npy",
    "year": 1992,
    "topic": "general",
    "chunk_index": 0
  },
  "1993_0": {
    "embedding_file": "embedding_1993_0.npy",
    "year": 1993,
    "topic": "general",
    "chunk_index": 0
  },
  "1994_0": {
    "embedding_file": "embedding_1994_0.npy",
    "year": 1994,
    "topic": "general",
    "chunk_index": 0
  },
  "1995_0": {
    "embedding_file": "embedding_1995_0.npy",
    "year": 1995,
    "topic": "general",
    "chunk_index": 0
  },
  "1996_0": {
    "embedding_file": "embedding_1996_0.npy",
    "year": 1996,
    "topic": "general",
    "chunk_index": 0
  },
  "1997_0": {
    "embedding_file": "embedding_1997_0.npy",
    "year": 1997,
    "topic": "general",
    "chunk_index": 0
  },
  "1998_0": {
    "embedding_file": "embedding_1998_0.npy",
    "year": 1998,
    "topic": "general",
    "chunk_index": 0
  },
  "1999_0": {
    "embedding_file": "embedding_1999_0.npy",
    "year": 1999,
    "topic": "general",
    "chunk_index": 0
  },
  "2000_0": {
    "embedding_file": "embedding_2000_0.npy",
    "year": 2000,
    "topic": "general",
    "chunk_index": 0
  },
  "2001_0": {
    "embedding_file": "embedding_2001_0.npy",
    "year": 2001,
    "topic": "general",
    "chunk_index": 0
  },
  "2002_0": {
    "embedding_file": "embedding_2002_0.npy",
    "year": 2002,
    "topic": "general",
    "chunk_index": 0
  },
  "2003_0": {
    "embedding_file": "embedding_2003_0.npy",
    "year": 2003,
    "topic": "financial_results",
    "chunk_index": 0
  },
  "2004_0": {
    "embedding_file": "embedding_2004_0.npy",
    "year": 2004,
    "topic": "insurance",
    "chunk_index": 0
  },
  "2004_1": {
    "embedding_file": "embedding_2004_1.npy",
    "year": 2004,
    "topic": "general",
    "chunk_index": 1
  },
  "2005_0": {
    "embedding_file": "embedding_2005_0.npy",
    "year": 2005,
    "topic": "insurance",
    "chunk_index": 0
  },
  "2005_1": {
    "embedding_file": "embedding_2005_1.npy",
    "year": 2005,
    "topic": "general",
    "chunk_index": 1
  },
  "2005_2": {
    "embedding_file": "embedding_2005_2.npy",
    "year": 2005,
    "topic": "general",
    "chunk_index": 2
  },
  "2006_0": {
    "embedding_file": "embedding_2006_0.npy",
    "year": 2006,
    "topic": "insurance",
    "chunk_index": 0
  },
  "2006_1": {
    "embedding_file": "embedding_2006_1.npy",
    "year": 2006,
    "topic": "general",
    "chunk_index": 1
  },
  "2007_0": {
    "embedding_file": "embedding_2007_0.npy",
    "year": 2007,
    "topic": "financial_results",
    "chunk_index": 0
  },
  "2007_1": {
    "embedding_file": "embedding_2007_1.npy",
    "year": 2007,
    "topic": "general",
    "chunk_index": 1
  },
  "2007_2": {
    "embedding_file": "embedding_2007_2.npy",
    "year": 2007,
    "topic": "general",
    "chunk_index": 2
  },
  "2008_0": {
    "embedding_file": "embedding_2008_0.npy",
    "year": 2008,
    "topic": "insurance",
    "chunk_index": 0
  },
  "2008_1": {
    "embedding_file": "embedding_2008_1.npy",
    "year": 2008,
    "topic": "general",
    "chunk_index": 1
  },
  "2008_2": {
    "embedding_file": "embedding_2008_2.npy",
    "year": 2008,
    "topic": "general",
    "chunk_index": 2
  },
  "2009_0": {
    "embedding_file": "embedding_2009_0.npy",
    "year": 2009,
    "topic": "insurance",
    "chunk_index": 0
  },
  "2009_1": {
    "embedding_file": "embedding_2009_1.npy",
    "year": 2009,
    "topic": "general",
    "chunk_index": 1
  },
  "2009_2": {
    "embedding_file": "embedding_2009_2.npy",
    "year": 2009,
    "topic": "general",
    "chunk_index": 2
  },
  "2010_0": {
    "embedding_file": "embedding_2010_0.npy",
    "year": 2010,
    "topic": "insurance",
    "chunk_index": 0
  },
  "2010_1": {
    "embedding_file": "embedding_2010_1.npy",
    "year": 2010,
    "topic": "general",
    "chunk_index": 1
  },
  "2010_2": {
    "embedding_file": "embedding_2010_2.npy",
    "year": 2010,
    "topic": "general",
    "chunk_index": 2
  },
  "2011_0": {
    "embedding_file": "embedding_2011_0.npy",
    "year": 2011,
    "topic": "insurance",
    "chunk_index": 0
  },
  "2011_1": {
    "embedding_file": "embedding_2011_1.npy",
    "year": 2011,
    "topic": "general",
    "chunk_index": 1
  },
  "2011_2": {
    "embedding_file": "embedding_2011_2.npy",
    "year": 2011,
    "topic": "general",
    "chunk_index": 2
  },
  "2012_0": {
    "embedding_file": "embedding_2012_0.npy",
    "year": 2012,
    "topic": "insurance",
    "chunk_index": 0
  },
  "2012_1": {
    "embedding_file": "embedding_2012_1.npy",
    "year": 2012,
    "topic": "general",
    "chunk_index": 1
  },
  "2013_0": {
    "embedding_file": "embedding_2013_0.npy",
    "year": 2013,
    "topic": "insurance",
    "chunk_index": 0
  },
  "2013_1": {
    "embedding_file": "embedding_2013_1.npy",
    "year": 2013,
    "topic": "general",
    "chunk_index": 1
  },
  "2013_2": {
    "embedding_file": "embedding_2013_2.npy",
    "year": 2013,
    "topic": "general",
    "chunk_index": 2
  },
  "2013_3": {
    "embedding_file": "embedding_2013_3.npy",
    "year": 2013,
    "topic": "general",
    "chunk_index": 3
  },
  "2014_0": {
    "embedding_file": "embedding_2014_0.npy",
    "year": 2014,
    "topic": "insurance",
    "chunk_index": 0
  },
  "2014_1": {
    "embedding_file": "embedding_2014_1.npy",
    "year": 2014,
    "topic": "general",
    "chunk_index": 1
  },
  "2014_2": {
    "embedding_file": "embedding_2014_2.npy",
    "year": 2014,
    "topic": "financial_results",
    "chunk_index": 2
  },
  "2014_3": {
    "embedding_file": "embedding_2014_3.npy",
    "year": 2014,
    "topic": "general",
    "chunk_index": 3
  },
  "2014_4": {
    "embedding_file": "embedding_2014_4.npy",
    "year": 2014,
    "topic": "general",
    "chunk_index": 4
  },
  "2015_0": {
    "embedding_file": "embedding_2015_0.npy",
    "year": 2015,
    "topic": "insurance",
    "chunk_index": 0
  },
  "2016_0": {
    "embedding_file": "embedding_2016_0.npy",
    "year": 2016,
    "topic": "insurance",
    "chunk_index": 0
  },
  "2016_1": {
    "embedding_file": "embedding_2016_1.npy",
    "year": 2016,
    "topic": "general",
    "chunk_index": 1
  },
  "2017_0": {
    "embedding_file": "embedding_2017_0.npy",
    "year": 2017,
    "topic": "insurance",
    "chunk_index": 0
  },
  "2018_0": {
    "embedding_file": "embedding_2018_0.npy",
    "year": 2018,
    "topic": "financial_results",
    "chunk_index": 0
  },
  "2019_0": {
    "embedding_file": "embedding_2019_0.npy",
    "year": 2019,
    "topic": "financial_results",
    "chunk_index": 0
  },
  "2020_0": {
    "embedding_file": "embedding_2020_0.npy",
    "year": 2020,
    "topic": "investments",
    "chunk_index": 0
  },
  "2021_0": {
    "embedding_file": "embedding_2021_0.npy",
    "year": 2021,
    "topic": "acquisitions",
    "chunk_index": 0
  },
  "2022_0": {
    "embedding_file": "embedding_2022_0.npy",
    "year": 2022,
    "topic": "business_performance",
    "chunk_index": 0
  },
  "2023_0": {
    "embedding_file": "embedding_2023_0.npy",
    "year": 2023,
    "topic": "financial_results",
    "chunk_index": 0
  }
}